{
  "locations": [
    {
      "geonames_id": 706483,
      "geonames_details": {
        "country_code": "UA",
        "country_name": "Ukraine",
        "lat": 49.98081,
        "lng": 36.25272,
        "name": "Kharkiv"
      }
    }
  ],
  "established": null,
  "external_ids": [
    {
      "type": "isni",
      "all": [
        "0000 0004 8309 4515"
      ],
      "preferred": "0000 0004 8309 4515"
    },
    {
      "type": "grid",
      "all": [
        "grid.445518.9"
      ],
      "preferred": "grid.445518.9"
    },
    {
      "type": "wikidata",
      "all": [
        "Q4496336"
      ],
      "preferred": "Q4496336"
    }
  ],
  "id": "https://ror.org/02pkshz09",
  "domains": [],
  "links": [
    {
      "type": "website",
      "value": "https://univd.edu.ua"
    }
  ],
  "names": [
    {
      "value": "Kharkiv National University of Internal Affairs",
      "types": [
        "ror_display",
        "label"
      ],
      "lang": null
    },
    {
      "value": "\u0425\u0430\u0440\u043a\u0456\u0432\u0441\u044c\u043a\u0438\u0439 \u043d\u0430\u0446\u0456\u043e\u043d\u0430\u043b\u044c\u043d\u0438\u0439 \u0443\u043d\u0456\u0432\u0435\u0440\u0441\u0438\u0442\u0435\u0442 \u0432\u043d\u0443\u0442\u0440\u0456\u0448\u043d\u0456\u0445 \u0441\u043f\u0440\u0430\u0432",
      "types": [
        "label"
      ],
      "lang": "uk"
    },
    {
      "value": "KhNUIA",
      "types": [
        "acronym"
      ],
      "lang": null
    }
  ],
  "relationships": [],
  "status": "active",
  "types": [
    "education"
  ],
  "admin": {
    "created": {
      "date": "2024-03-15",
      "schema_version": "1.0"
    },
    "last_modified": {
      "date": "2024-03-15",
      "schema_version": "2.0"
    }
  }
}