{
  "id": "https://ror.org/04xeap310",
  "name": "UIN SATU Tulungagung",
  "email_address": null,
  "ip_addresses": [],
  "established": 1968,
  "types": [
    "Education"
  ],
  "relationships": [],
  "addresses": [
    {
      "lat": -8.0657,
      "lng": 111.9025,
      "state": null,
      "state_code": null,
      "city": "Tulungagung",
      "geonames_city": {
        "id": 1623080,
        "city": "Tulungagung",
        "geonames_admin1": {
          "ascii_name": null,
          "code": null,
          "id": null,
          "name": null
        },
        "geonames_admin2": {
          "ascii_name": null,
          "code": null,
          "id": null,
          "name": null
        },
        "license": {
          "attribution": "Data from geonames.org under a CC-BY 3.0 license",
          "license": "http://creativecommons.org/licenses/by/3.0/"
        },
        "nuts_level1": {
          "code": null,
          "name": null
        },
        "nuts_level2": {
          "code": null,
          "name": null
        },
        "nuts_level3": {
          "code": null,
          "name": null
        }
      },
      "postcode": null,
      "primary": false,
      "line": null,
      "country_geonames_id": null
    }
  ],
  "links": [
    "https://www.uinsatu.ac.id"
  ],
  "aliases": [
    "IAIN Tulungagung",
    "Institut Agama Islam Negeri Tulungagung",
    "Sayyid Ali Rahmatullah State Islamic University Tulungagung",
    "UIN Sayyid Ali Rahmatullah Tulungagung",
    "Universitas Islam Negeri Sayyid Ali Rahmatullah Tulungagung"
  ],
  "acronyms": [
    "UIN SATU"
  ],
  "status": "active",
  "wikipedia_url": "https://id.wikipedia.org/wiki/Universitas_Islam_Negeri_Sayyid_Ali_Rahmatullah_Tulungagung",
  "labels": [],
  "country": {
    "country_name": "Indonesia",
    "country_code": "ID"
  },
  "external_ids": {
    "Wikidata": {
      "all": [
        "Q19726445"
      ],
      "preferred": "Q19726445"
    }
  }
}