{
  "id": "https://ror.org/01bwma613",
  "name": "Max Planck School Matter to Life",
  "email_address": null,
  "ip_addresses": [],
  "established": 2018,
  "types": [
    "Education"
  ],
  "relationships": [],
  "addresses": [
    {
      "lat": 49.40768,
      "lng": 8.69079,
      "state": null,
      "state_code": null,
      "city": "Heidelberg",
      "geonames_city": {
        "id": 2907911,
        "city": "Heidelberg",
        "geonames_admin1": {
          "ascii_name": null,
          "code": null,
          "id": null,
          "name": null
        },
        "geonames_admin2": {
          "ascii_name": null,
          "code": null,
          "id": null,
          "name": null
        },
        "license": {
          "attribution": "Data from geonames.org under a CC-BY 3.0 license",
          "license": "http://creativecommons.org/licenses/by/3.0/"
        },
        "nuts_level1": {
          "code": null,
          "name": null
        },
        "nuts_level2": {
          "code": null,
          "name": null
        },
        "nuts_level3": {
          "code": null,
          "name": null
        }
      },
      "postcode": null,
      "primary": false,
      "line": null,
      "country_geonames_id": null
    }
  ],
  "links": [
    "https://mattertolife.maxplanckschools.org"
  ],
  "aliases": [
    "Matter to Life"
  ],
  "acronyms": [
    "MtL"
  ],
  "status": "active",
  "wikipedia_url": null,
  "labels": [],
  "country": {
    "country_name": "Germany",
    "country_code": "DE"
  },
  "external_ids": {}
}