{
  "id": "https://ror.org/0237c2m81",
  "name": "HCA Healthcare",
  "email_address": null,
  "ip_addresses": [],
  "established": 1968,
  "types": [
    "Healthcare"
  ],
  "relationships": [
    {
      "label": "Mercy Hospital",
      "type": "Child",
      "id": "https://ror.org/05rsdqb94"
    },
    {
      "label": "Menorah Medical Center",
      "type": "Related",
      "id": "https://ror.org/01w6z0f95"
    }
  ],
  "addresses": [
    {
      "lat": 36.16589,
      "lng": -86.78444,
      "state": null,
      "state_code": null,
      "city": "Nashville",
      "geonames_city": {
        "id": 4644585,
        "city": "Nashville",
        "geonames_admin1": {
          "ascii_name": null,
          "code": null,
          "id": null,
          "name": null
        },
        "geonames_admin2": {
          "ascii_name": null,
          "code": null,
          "id": null,
          "name": null
        },
        "license": {
          "attribution": "Data from geonames.org under a CC-BY 3.0 license",
          "license": "http://creativecommons.org/licenses/by/3.0/"
        },
        "nuts_level1": {
          "code": null,
          "name": null
        },
        "nuts_level2": {
          "code": null,
          "name": null
        },
        "nuts_level3": {
          "code": null,
          "name": null
        }
      },
      "postcode": null,
      "primary": false,
      "line": null,
      "country_geonames_id": null
    }
  ],
  "links": [
    "https://hcahealthcare.com"
  ],
  "aliases": [
    "Hospital Corporation of America"
  ],
  "acronyms": [
    "HCA"
  ],
  "status": "active",
  "wikipedia_url": "https://en.wikipedia.org/wiki/Hospital_Corporation_of_America",
  "labels": [],
  "country": {
    "country_name": "United States",
    "country_code": "US"
  },
  "external_ids": {
    "GRID": {
      "all": "grid.414420.7",
      "preferred": "grid.414420.7"
    },
    "ISNI": {
      "all": [
        "0000 0001 0158 6152"
      ],
      "preferred": null
    },
    "Wikidata": {
      "all": [
        "Q1630431"
      ],
      "preferred": null
    }
  }
}