{
  "id": "https://ror.org/02gam0808",
  "name": "Centre d'Etudes et de Recherche en Gestion d'Aix-Marseille",
  "email_address": null,
  "ip_addresses": [],
  "established": 2008,
  "types": [
    "Facility"
  ],
  "relationships": [
    {
      "label": "Université de Toulon",
      "type": "Parent",
      "id": "https://ror.org/02m9kbe37"
    }
  ],
  "addresses": [
    {
      "lat": 43.12442,
      "lng": 5.92836,
      "state": null,
      "state_code": null,
      "city": "Toulon",
      "geonames_city": {
        "id": 2972328,
        "city": "Toulon",
        "geonames_admin1": {
          "ascii_name": null,
          "code": null,
          "id": null,
          "name": null
        },
        "geonames_admin2": {
          "ascii_name": null,
          "code": null,
          "id": null,
          "name": null
        },
        "license": {
          "attribution": "Data from geonames.org under a CC-BY 3.0 license",
          "license": "http://creativecommons.org/licenses/by/3.0/"
        },
        "nuts_level1": {
          "code": null,
          "name": null
        },
        "nuts_level2": {
          "code": null,
          "name": null
        },
        "nuts_level3": {
          "code": null,
          "name": null
        }
      },
      "postcode": null,
      "primary": false,
      "line": null,
      "country_geonames_id": null
    }
  ],
  "links": [
    "https://cergam.univ-amu.fr"
  ],
  "aliases": [],
  "acronyms": [
    "CERGAM"
  ],
  "status": "active",
  "wikipedia_url": null,
  "labels": [],
  "country": {
    "country_name": "France",
    "country_code": "FR"
  },
  "external_ids": {
    "Wikidata": {
      "all": [
        "Q51784656"
      ],
      "preferred": "Q51784656"
    }
  }
}