{
  "id": "https://ror.org/03fsckq75",
  "name": "Ho Chi Minh University of Banking",
  "email_address": null,
  "ip_addresses": [],
  "established": 1976,
  "types": [
    "Education"
  ],
  "relationships": [],
  "addresses": [
    {
      "lat": 10.82302,
      "lng": 106.62965,
      "state": null,
      "state_code": null,
      "city": "Ho Chi Minh City",
      "geonames_city": {
        "id": 1566083,
        "city": "Ho Chi Minh City",
        "geonames_admin1": {
          "ascii_name": null,
          "code": null,
          "id": null,
          "name": null
        },
        "geonames_admin2": {
          "ascii_name": null,
          "code": null,
          "id": null,
          "name": null
        },
        "license": {
          "attribution": "Data from geonames.org under a CC-BY 3.0 license",
          "license": "http://creativecommons.org/licenses/by/3.0/"
        },
        "nuts_level1": {
          "code": null,
          "name": null
        },
        "nuts_level2": {
          "code": null,
          "name": null
        },
        "nuts_level3": {
          "code": null,
          "name": null
        }
      },
      "postcode": null,
      "primary": false,
      "line": null,
      "country_geonames_id": null
    }
  ],
  "links": [
    "https://hub.edu.vn"
  ],
  "aliases": [
    "Banking University of Ho Chi Minh City",
    "Đại học Ngân hàng TP.HCM"
  ],
  "acronyms": [
    "BUH",
    "HUB"
  ],
  "status": "active",
  "wikipedia_url": "https://en.wikipedia.org/wiki/Banking_University_of_Ho_Chi_Minh_City",
  "labels": [
    {
      "label": "Trường Đại học Ngân hàng Thành phố Hồ Chí Minh",
      "iso639": "vi"
    }
  ],
  "country": {
    "country_name": "Vietnam",
    "country_code": "VN"
  },
  "external_ids": {
    "GRID": {
      "all": "grid.444834.b",
      "preferred": "grid.444834.b"
    },
    "ISNI": {
      "all": [
        "0000 0004 4660 2058"
      ],
      "preferred": null
    },
    "Wikidata": {
      "all": [
        "Q4856328"
      ],
      "preferred": null
    }
  }
}