{
  "id": "https://ror.org/01ndzg854",
  "name": "Xinjiang University of Science and Technology",
  "email_address": null,
  "ip_addresses": [],
  "established": 2019,
  "types": [
    "Education"
  ],
  "relationships": [],
  "addresses": [
    {
      "lat": 41.76055,
      "lng": 86.15231,
      "state": null,
      "state_code": null,
      "city": "Korla",
      "geonames_city": {
        "id": 1529376,
        "city": "Korla",
        "geonames_admin1": {
          "ascii_name": null,
          "code": null,
          "id": null,
          "name": null
        },
        "geonames_admin2": {
          "ascii_name": null,
          "code": null,
          "id": null,
          "name": null
        },
        "license": {
          "attribution": "Data from geonames.org under a CC-BY 3.0 license",
          "license": "http://creativecommons.org/licenses/by/3.0/"
        },
        "nuts_level1": {
          "code": null,
          "name": null
        },
        "nuts_level2": {
          "code": null,
          "name": null
        },
        "nuts_level3": {
          "code": null,
          "name": null
        }
      },
      "postcode": null,
      "primary": false,
      "line": null,
      "country_geonames_id": null
    }
  ],
  "links": [
    "https://www.xjust.edu.cn"
  ],
  "aliases": [
    "Xinjiang College of Science & Technology",
    "Xinjiang College of Science and Technology"
  ],
  "acronyms": [
    "XJUST"
  ],
  "status": "active",
  "wikipedia_url": "https://zh.wikipedia.org/wiki/%E6%96%B0%E7%96%86%E7%A7%91%E6%8A%80%E5%AD%A6%E9%99%A2",
  "labels": [
    {
      "label": "新疆科技学院",
      "iso639": "zh"
    }
  ],
  "country": {
    "country_name": "China",
    "country_code": "CN"
  },
  "external_ids": {
    "Wikidata": {
      "all": [
        "Q97347483"
      ],
      "preferred": "Q97347483"
    }
  }
}