{
  "id": "https://ror.org/03j0zz815",
  "name": "Synsint Research Group",
  "email_address": null,
  "ip_addresses": [],
  "established": 2021,
  "types": [
    "Nonprofit"
  ],
  "relationships": [],
  "addresses": [
    {
      "lat": 35.12489,
      "lng": 33.94135,
      "state": null,
      "state_code": null,
      "city": "Famagusta",
      "geonames_city": {
        "id": 146617,
        "city": "Famagusta",
        "geonames_admin1": {
          "ascii_name": null,
          "code": null,
          "id": null,
          "name": null
        },
        "geonames_admin2": {
          "ascii_name": null,
          "code": null,
          "id": null,
          "name": null
        },
        "license": {
          "attribution": "Data from geonames.org under a CC-BY 3.0 license",
          "license": "http://creativecommons.org/licenses/by/3.0/"
        },
        "nuts_level1": {
          "code": null,
          "name": null
        },
        "nuts_level2": {
          "code": null,
          "name": null
        },
        "nuts_level3": {
          "code": null,
          "name": null
        }
      },
      "postcode": null,
      "primary": false,
      "line": null,
      "country_geonames_id": null
    }
  ],
  "links": [
    "https://www.synsint.org"
  ],
  "aliases": [],
  "acronyms": [
    "SRG"
  ],
  "status": "active",
  "wikipedia_url": null,
  "labels": [],
  "country": {
    "country_name": "Cyprus",
    "country_code": "CY"
  },
  "external_ids": {
    "Wikidata": {
      "all": [
        "Q125526311"
      ],
      "preferred": "Q125526311"
    }
  }
}