{
  "id": "https://ror.org/003k26w86",
  "name": "Institut de Recherche et de Documentation en Économie de la Santé",
  "email_address": null,
  "ip_addresses": [],
  "established": 1985,
  "types": [
    "Education"
  ],
  "relationships": [],
  "addresses": [
    {
      "lat": 48.85341,
      "lng": 2.3488,
      "state": null,
      "state_code": null,
      "city": "Paris",
      "geonames_city": {
        "id": 2988507,
        "city": "Paris",
        "geonames_admin1": {
          "ascii_name": null,
          "code": "FR.IDF",
          "id": null,
          "name": "Île-de-France"
        },
        "geonames_admin2": {
          "ascii_name": null,
          "code": null,
          "id": null,
          "name": null
        },
        "license": {
          "attribution": "Data from geonames.org under a CC-BY 3.0 license",
          "license": "http://creativecommons.org/licenses/by/3.0/"
        },
        "nuts_level1": {
          "code": null,
          "name": null
        },
        "nuts_level2": {
          "code": null,
          "name": null
        },
        "nuts_level3": {
          "code": null,
          "name": null
        }
      },
      "postcode": null,
      "primary": false,
      "line": null,
      "country_geonames_id": null
    }
  ],
  "links": [
    "https://www.irdes.fr/"
  ],
  "aliases": [
    "Centre de Recherche, d'Etudes et de Documentation en Economie de la Santé"
  ],
  "acronyms": [
    "CREDES",
    "IRDES"
  ],
  "status": "active",
  "wikipedia_url": null,
  "labels": [
    {
      "label": "Institute for Research and Information in Health Economics",
      "iso639": "en"
    }
  ],
  "country": {
    "country_name": "France",
    "country_code": "FR"
  },
  "external_ids": {
    "GRID": {
      "all": "grid.435473.2",
      "preferred": "grid.435473.2"
    },
    "ISNI": {
      "all": [
        "0000 0004 0633 0537"
      ],
      "preferred": null
    },
    "Wikidata": {
      "all": [
        "Q3152096"
      ],
      "preferred": null
    }
  }
}