{
  "id": "https://ror.org/01t884y44",
  "name": "University of Greater Manchester",
  "email_address": null,
  "ip_addresses": [],
  "established": 1982,
  "types": [
    "Education",
    "Funder"
  ],
  "relationships": [],
  "addresses": [
    {
      "lat": 53.58333,
      "lng": -2.43333,
      "state": null,
      "state_code": null,
      "city": "Bolton",
      "geonames_city": {
        "id": 2655237,
        "city": "Bolton",
        "geonames_admin1": {
          "ascii_name": null,
          "code": "GB.ENG",
          "id": null,
          "name": "England"
        },
        "geonames_admin2": {
          "ascii_name": null,
          "code": null,
          "id": null,
          "name": null
        },
        "license": {
          "attribution": "Data from geonames.org under a CC-BY 3.0 license",
          "license": "http://creativecommons.org/licenses/by/3.0/"
        },
        "nuts_level1": {
          "code": null,
          "name": null
        },
        "nuts_level2": {
          "code": null,
          "name": null
        },
        "nuts_level3": {
          "code": null,
          "name": null
        }
      },
      "postcode": null,
      "primary": false,
      "line": null,
      "country_geonames_id": null
    }
  ],
  "links": [
    "https://greatermanchester.ac.uk"
  ],
  "aliases": [
    "Bolton Institute",
    "Bolton Institute of Higher Education",
    "University of Bolton"
  ],
  "acronyms": [],
  "status": "active",
  "wikipedia_url": "http://en.wikipedia.org/wiki/University_of_Bolton",
  "labels": [],
  "country": {
    "country_name": "United Kingdom",
    "country_code": "GB"
  },
  "external_ids": {
    "FundRef": {
      "all": [
        "100010042"
      ],
      "preferred": null
    },
    "GRID": {
      "all": "grid.36076.34",
      "preferred": "grid.36076.34"
    },
    "ISNI": {
      "all": [
        "0000 0001 2166 3186"
      ],
      "preferred": null
    },
    "Wikidata": {
      "all": [
        "Q1683230"
      ],
      "preferred": null
    }
  }
}