{
  "id": "https://ror.org/03b8ydc26",
  "name": "Ciro",
  "email_address": null,
  "ip_addresses": [],
  "established": 1985,
  "types": [
    "Healthcare"
  ],
  "relationships": [],
  "addresses": [
    {
      "lat": 52.6425,
      "lng": 5.05972,
      "state": null,
      "state_code": null,
      "city": "Hoorn",
      "geonames_city": {
        "id": 2753638,
        "city": "Hoorn",
        "geonames_admin1": {
          "ascii_name": null,
          "code": "NL.NH",
          "id": null,
          "name": "North Holland"
        },
        "geonames_admin2": {
          "ascii_name": null,
          "code": null,
          "id": null,
          "name": null
        },
        "license": {
          "attribution": "Data from geonames.org under a CC-BY 3.0 license",
          "license": "http://creativecommons.org/licenses/by/3.0/"
        },
        "nuts_level1": {
          "code": null,
          "name": null
        },
        "nuts_level2": {
          "code": null,
          "name": null
        },
        "nuts_level3": {
          "code": null,
          "name": null
        }
      },
      "postcode": null,
      "primary": false,
      "line": null,
      "country_geonames_id": null
    }
  ],
  "links": [
    "https://www.ciro-horn.nl"
  ],
  "aliases": [],
  "acronyms": [],
  "status": "active",
  "wikipedia_url": null,
  "labels": [],
  "country": {
    "country_name": "The Netherlands",
    "country_code": "NL"
  },
  "external_ids": {
    "GRID": {
      "all": "grid.491136.8",
      "preferred": "grid.491136.8"
    },
    "ISNI": {
      "all": [
        "0000 0004 8497 4987"
      ],
      "preferred": "0000 0004 8497 4987"
    }
  }
}