{
  "id": "https://ror.org/03eqe9f63",
  "name": "Hospital Universitario de la Samaritana",
  "email_address": null,
  "ip_addresses": [],
  "established": 1933,
  "types": [
    "Healthcare"
  ],
  "relationships": [],
  "addresses": [
    {
      "lat": 4.60971,
      "lng": -74.08175,
      "state": null,
      "state_code": null,
      "city": "Bogotá",
      "geonames_city": {
        "id": 3688689,
        "city": "Bogotá",
        "geonames_admin1": {
          "ascii_name": null,
          "code": "CO.DC",
          "id": null,
          "name": "Bogota D.C."
        },
        "geonames_admin2": {
          "ascii_name": null,
          "code": null,
          "id": null,
          "name": null
        },
        "license": {
          "attribution": "Data from geonames.org under a CC-BY 3.0 license",
          "license": "http://creativecommons.org/licenses/by/3.0/"
        },
        "nuts_level1": {
          "code": null,
          "name": null
        },
        "nuts_level2": {
          "code": null,
          "name": null
        },
        "nuts_level3": {
          "code": null,
          "name": null
        }
      },
      "postcode": null,
      "primary": false,
      "line": null,
      "country_geonames_id": null
    }
  ],
  "links": [
    "https://www.hus.org.co/"
  ],
  "aliases": [],
  "acronyms": [
    "HUS"
  ],
  "status": "active",
  "wikipedia_url": null,
  "labels": [
    {
      "label": "University Hospital of the Samaritan",
      "iso639": "en"
    }
  ],
  "country": {
    "country_name": "Colombia",
    "country_code": "CO"
  },
  "external_ids": {
    "GRID": {
      "all": "grid.459557.f",
      "preferred": "grid.459557.f"
    },
    "ISNI": {
      "all": [
        "0000 0004 0447 4553"
      ],
      "preferred": null
    }
  }
}