{
  "id": "https://ror.org/03ph49z03",
  "name": "Islamic University in Uganda",
  "email_address": null,
  "ip_addresses": [],
  "established": 1988,
  "types": [
    "Education"
  ],
  "relationships": [
    {
      "label": "Kibuli Hospital",
      "type": "Related",
      "id": "https://ror.org/03nhtqr81"
    }
  ],
  "addresses": [
    {
      "lat": 1.08209,
      "lng": 34.17503,
      "state": null,
      "state_code": null,
      "city": "Mbale",
      "geonames_city": {
        "id": 229278,
        "city": "Mbale",
        "geonames_admin1": {
          "ascii_name": null,
          "code": "UG.E",
          "id": null,
          "name": "Eastern Region"
        },
        "geonames_admin2": {
          "ascii_name": null,
          "code": null,
          "id": null,
          "name": null
        },
        "license": {
          "attribution": "Data from geonames.org under a CC-BY 3.0 license",
          "license": "http://creativecommons.org/licenses/by/3.0/"
        },
        "nuts_level1": {
          "code": null,
          "name": null
        },
        "nuts_level2": {
          "code": null,
          "name": null
        },
        "nuts_level3": {
          "code": null,
          "name": null
        }
      },
      "postcode": null,
      "primary": false,
      "line": null,
      "country_geonames_id": null
    }
  ],
  "links": [
    "https://iuiu.ac.ug"
  ],
  "aliases": [],
  "acronyms": [
    "IUIU"
  ],
  "status": "active",
  "wikipedia_url": "https://en.wikipedia.org/wiki/Islamic_University_in_Uganda",
  "labels": [],
  "country": {
    "country_name": "Uganda",
    "country_code": "UG"
  },
  "external_ids": {
    "GRID": {
      "all": "grid.442655.4",
      "preferred": "grid.442655.4"
    },
    "ISNI": {
      "all": [
        "0000 0001 0042 4901"
      ],
      "preferred": null
    },
    "Wikidata": {
      "all": [
        "Q5158982"
      ],
      "preferred": null
    }
  }
}