{
  "id": "https://ror.org/051a9ap09",
  "name": "Bibliotheca Alexandrina",
  "email_address": null,
  "ip_addresses": [],
  "established": 2002,
  "types": [
    "Archive"
  ],
  "relationships": [],
  "addresses": [
    {
      "lat": 31.20176,
      "lng": 29.91582,
      "state": null,
      "state_code": null,
      "city": "Alexandria",
      "geonames_city": {
        "id": 361058,
        "city": "Alexandria",
        "geonames_admin1": {
          "ascii_name": null,
          "code": "EG.ALX",
          "id": null,
          "name": "Alexandria"
        },
        "geonames_admin2": {
          "ascii_name": null,
          "code": null,
          "id": null,
          "name": null
        },
        "license": {
          "attribution": "Data from geonames.org under a CC-BY 3.0 license",
          "license": "http://creativecommons.org/licenses/by/3.0/"
        },
        "nuts_level1": {
          "code": null,
          "name": null
        },
        "nuts_level2": {
          "code": null,
          "name": null
        },
        "nuts_level3": {
          "code": null,
          "name": null
        }
      },
      "postcode": null,
      "primary": false,
      "line": null,
      "country_geonames_id": null
    }
  ],
  "links": [
    "https://bibalex.org/en/default"
  ],
  "aliases": [
    "Maktabat al-Iskandarīyah"
  ],
  "acronyms": [],
  "status": "active",
  "wikipedia_url": "https://en.wikipedia.org/wiki/Bibliotheca_Alexandrina",
  "labels": [
    {
      "label": "Center for Documentation of Cultural and Natural Heritage",
      "iso639": "en"
    },
    {
      "label": "مكتبة الإسكندرية",
      "iso639": "ar"
    }
  ],
  "country": {
    "country_name": "Egypt",
    "country_code": "EG"
  },
  "external_ids": {
    "GRID": {
      "all": "grid.433309.e",
      "preferred": "grid.433309.e"
    },
    "ISNI": {
      "all": [
        "0000 0001 2257 3510"
      ],
      "preferred": null
    },
    "Wikidata": {
      "all": [
        "Q501851",
        "Q5059593"
      ],
      "preferred": "Q501851"
    }
  }
}