{
  "id": "https://ror.org/0576vga12",
  "name": "Vasyl Stefanyk Carpathian National University",
  "email_address": null,
  "ip_addresses": [],
  "established": 1940,
  "types": [
    "Education"
  ],
  "relationships": [],
  "addresses": [
    {
      "lat": 48.92312,
      "lng": 24.71248,
      "state": null,
      "state_code": null,
      "city": "Ivano-Frankivsk",
      "geonames_city": {
        "id": 707471,
        "city": "Ivano-Frankivsk",
        "geonames_admin1": {
          "ascii_name": null,
          "code": "UA.26",
          "id": null,
          "name": "Ivano-Frankivsk"
        },
        "geonames_admin2": {
          "ascii_name": null,
          "code": null,
          "id": null,
          "name": null
        },
        "license": {
          "attribution": "Data from geonames.org under a CC-BY 3.0 license",
          "license": "http://creativecommons.org/licenses/by/3.0/"
        },
        "nuts_level1": {
          "code": null,
          "name": null
        },
        "nuts_level2": {
          "code": null,
          "name": null
        },
        "nuts_level3": {
          "code": null,
          "name": null
        }
      },
      "postcode": null,
      "primary": false,
      "line": null,
      "country_geonames_id": null
    }
  ],
  "links": [
    "https://cnu.edu.ua"
  ],
  "aliases": [
    "Podkarpacki Uniwersytet Narodowy im. Wasyla Stefanyka",
    "Vasyl Stefanyk Precarpathian National University",
    "Прикарпатский национальный университет имени Василия Стефаника",
    "Прикарпатський національний університет імені Василя Стефаника"
  ],
  "acronyms": [],
  "status": "active",
  "wikipedia_url": "https://en.wikipedia.org/wiki/Vasyl_Stefanyk_Precarpathian_National_University",
  "labels": [
    {
      "label": "Karpacki Narodowy Uniwersytet imienia Wasyla Stefanyka",
      "iso639": "pl"
    },
    {
      "label": "Карпатський національний університет імені Василя Стефаника",
      "iso639": "uk"
    }
  ],
  "country": {
    "country_name": "Ukraine",
    "country_code": "UA"
  },
  "external_ids": {
    "GRID": {
      "all": "grid.445463.4",
      "preferred": "grid.445463.4"
    },
    "ISNI": {
      "all": [
        "0000 0004 6478 1758"
      ],
      "preferred": null
    },
    "Wikidata": {
      "all": [
        "Q1131169"
      ],
      "preferred": null
    }
  }
}