{
  "id": "https://ror.org/05jqw2r29",
  "name": "Rossdales Veterinary Surgeons",
  "email_address": null,
  "ip_addresses": [],
  "established": 1959,
  "types": [
    "Healthcare"
  ],
  "relationships": [],
  "addresses": [
    {
      "lat": 52.24467,
      "lng": 0.40418,
      "state": null,
      "state_code": null,
      "city": "Newmarket",
      "geonames_city": {
        "id": 2641616,
        "city": "Newmarket",
        "geonames_admin1": {
          "ascii_name": null,
          "code": "GB.ENG",
          "id": null,
          "name": "England"
        },
        "geonames_admin2": {
          "ascii_name": null,
          "code": null,
          "id": null,
          "name": null
        },
        "license": {
          "attribution": "Data from geonames.org under a CC-BY 3.0 license",
          "license": "http://creativecommons.org/licenses/by/3.0/"
        },
        "nuts_level1": {
          "code": null,
          "name": null
        },
        "nuts_level2": {
          "code": null,
          "name": null
        },
        "nuts_level3": {
          "code": null,
          "name": null
        }
      },
      "postcode": null,
      "primary": false,
      "line": null,
      "country_geonames_id": null
    }
  ],
  "links": [
    "https://www.rossdales.com/"
  ],
  "aliases": [
    "Rossdales Equine Hospital"
  ],
  "acronyms": [],
  "status": "active",
  "wikipedia_url": null,
  "labels": [],
  "country": {
    "country_name": "United Kingdom",
    "country_code": "GB"
  },
  "external_ids": {
    "GRID": {
      "all": "grid.500832.c",
      "preferred": "grid.500832.c"
    },
    "Wikidata": {
      "all": [
        "Q61930696"
      ],
      "preferred": null
    }
  }
}