{
  "id": "https://ror.org/00mgjz918",
  "name": "Instituto Superior de Angola",
  "email_address": null,
  "ip_addresses": [],
  "established": 2012,
  "types": [
    "Education"
  ],
  "relationships": [],
  "addresses": [
    {
      "lat": -8.83682,
      "lng": 13.23432,
      "state": null,
      "state_code": null,
      "city": "Luanda",
      "geonames_city": {
        "id": 2240449,
        "city": "Luanda",
        "geonames_admin1": {
          "ascii_name": null,
          "code": null,
          "id": null,
          "name": null
        },
        "geonames_admin2": {
          "ascii_name": null,
          "code": null,
          "id": null,
          "name": null
        },
        "license": {
          "attribution": "Data from geonames.org under a CC-BY 3.0 license",
          "license": "http://creativecommons.org/licenses/by/3.0/"
        },
        "nuts_level1": {
          "code": null,
          "name": null
        },
        "nuts_level2": {
          "code": null,
          "name": null
        },
        "nuts_level3": {
          "code": null,
          "name": null
        }
      },
      "postcode": null,
      "primary": false,
      "line": null,
      "country_geonames_id": null
    }
  ],
  "links": [
    "https://isa.ao"
  ],
  "aliases": [
    "Higher Institute of Angola"
  ],
  "acronyms": [
    "ISA"
  ],
  "status": "active",
  "wikipedia_url": null,
  "labels": [],
  "country": {
    "country_name": "Angola",
    "country_code": "AO"
  },
  "external_ids": {}
}