{
  "id": "https://ror.org/02yknsc93",
  "name": "McCoy College of Education",
  "email_address": null,
  "ip_addresses": [],
  "established": 2014,
  "types": [
    "Education"
  ],
  "relationships": [],
  "addresses": [
    {
      "lat": 10.28835,
      "lng": -2.60889,
      "state": null,
      "state_code": null,
      "city": "Nadowli",
      "geonames_city": {
        "id": 7647177,
        "city": "Nadowli",
        "geonames_admin1": {
          "ascii_name": null,
          "code": null,
          "id": null,
          "name": null
        },
        "geonames_admin2": {
          "ascii_name": null,
          "code": null,
          "id": null,
          "name": null
        },
        "license": {
          "attribution": "Data from geonames.org under a CC-BY 3.0 license",
          "license": "http://creativecommons.org/licenses/by/3.0/"
        },
        "nuts_level1": {
          "code": null,
          "name": null
        },
        "nuts_level2": {
          "code": null,
          "name": null
        },
        "nuts_level3": {
          "code": null,
          "name": null
        }
      },
      "postcode": null,
      "primary": false,
      "line": null,
      "country_geonames_id": null
    }
  ],
  "links": [
    "https://mccoycoe.edu.gh"
  ],
  "aliases": [
    "McCoy COE"
  ],
  "acronyms": [],
  "status": "active",
  "wikipedia_url": null,
  "labels": [],
  "country": {
    "country_name": "Ghana",
    "country_code": "GH"
  },
  "external_ids": {
    "Wikidata": {
      "all": [
        "Q126911819"
      ],
      "preferred": "Q126911819"
    }
  }
}