{
  "id": "https://ror.org/00q3xz126",
  "name": "Roswell Park Comprehensive Cancer Center",
  "email_address": null,
  "ip_addresses": [],
  "established": null,
  "types": [
    "Healthcare"
  ],
  "relationships": [
    {
      "label": "Roswell Park Comprehensive Cancer Center",
      "type": "Successor",
      "id": "https://ror.org/0499dwk57"
    }
  ],
  "addresses": [
    {
      "lat": 42.88645,
      "lng": -78.87837,
      "state": null,
      "state_code": null,
      "city": "Buffalo",
      "geonames_city": {
        "id": 5110629,
        "city": "Buffalo",
        "geonames_admin1": {
          "ascii_name": null,
          "code": null,
          "id": null,
          "name": null
        },
        "geonames_admin2": {
          "ascii_name": null,
          "code": null,
          "id": null,
          "name": null
        },
        "license": {
          "attribution": "Data from geonames.org under a CC-BY 3.0 license",
          "license": "http://creativecommons.org/licenses/by/3.0/"
        },
        "nuts_level1": {
          "code": null,
          "name": null
        },
        "nuts_level2": {
          "code": null,
          "name": null
        },
        "nuts_level3": {
          "code": null,
          "name": null
        }
      },
      "postcode": null,
      "primary": false,
      "line": null,
      "country_geonames_id": null
    }
  ],
  "links": [
    "https://www.roswellpark.org"
  ],
  "aliases": [
    "Roswell Park Cancer Center"
  ],
  "acronyms": [],
  "status": "withdrawn",
  "wikipedia_url": "https://en.wikipedia.org/wiki/Roswell_Park_Comprehensive_Cancer_Center",
  "labels": [],
  "country": {
    "country_name": "United States",
    "country_code": "US"
  },
  "external_ids": {}
}