{
  "id": "https://ror.org/01pf7nz88",
  "name": "French National Agency for Water and Aquatic Environments",
  "email_address": null,
  "ip_addresses": [],
  "established": 2007,
  "types": [
    "Government"
  ],
  "relationships": [
    {
      "label": "Ministère de la Transition écologique et de la Cohésion des territoires",
      "type": "Parent",
      "id": "https://ror.org/00g8rx069"
    }
  ],
  "addresses": [
    {
      "lat": 48.8486,
      "lng": 2.43769,
      "state": null,
      "state_code": null,
      "city": "Vincennes",
      "geonames_city": {
        "id": 2968054,
        "city": "Vincennes",
        "geonames_admin1": {
          "ascii_name": null,
          "code": null,
          "id": null,
          "name": null
        },
        "geonames_admin2": {
          "ascii_name": null,
          "code": null,
          "id": null,
          "name": null
        },
        "license": {
          "attribution": "Data from geonames.org under a CC-BY 3.0 license",
          "license": "http://creativecommons.org/licenses/by/3.0/"
        },
        "nuts_level1": {
          "code": null,
          "name": null
        },
        "nuts_level2": {
          "code": null,
          "name": null
        },
        "nuts_level3": {
          "code": null,
          "name": null
        }
      },
      "postcode": null,
      "primary": false,
      "line": null,
      "country_geonames_id": null
    }
  ],
  "links": [
    "http://www.onema.fr/sites/default/files/EN/EV/index.html"
  ],
  "aliases": [],
  "acronyms": [
    "ONEMA"
  ],
  "status": "inactive",
  "wikipedia_url": null,
  "labels": [
    {
      "label": "Agence Française Pour la Biodiversité",
      "iso639": "fr"
    }
  ],
  "country": {
    "country_name": "France",
    "country_code": "FR"
  },
  "external_ids": {
    "FundRef": {
      "all": [
        "501100011569"
      ],
      "preferred": "501100011569"
    },
    "GRID": {
      "all": "grid.484148.5",
      "preferred": "grid.484148.5"
    },
    "ISNI": {
      "all": [
        "0000 0000 9573 5069"
      ],
      "preferred": null
    }
  }
}