{
  "id": "https://ror.org/033ebya06",
  "name": "UMR BIOdiversity, GEnes & Communities",
  "email_address": null,
  "ip_addresses": [],
  "established": null,
  "types": [
    "Facility"
  ],
  "relationships": [
    {
      "label": "Institut National de Recherche pour l'Agriculture, l'Alimentation et l'Environnement",
      "type": "Parent",
      "id": "https://ror.org/003vg9w96"
    },
    {
      "label": "Université de Bordeaux",
      "type": "Parent",
      "id": "https://ror.org/057qpr032"
    }
  ],
  "addresses": [
    {
      "lat": 44.80849,
      "lng": -0.58915,
      "state": null,
      "state_code": null,
      "city": "Talence",
      "geonames_city": {
        "id": 2973495,
        "city": "Talence",
        "geonames_admin1": {
          "ascii_name": null,
          "code": null,
          "id": null,
          "name": null
        },
        "geonames_admin2": {
          "ascii_name": null,
          "code": null,
          "id": null,
          "name": null
        },
        "license": {
          "attribution": "Data from geonames.org under a CC-BY 3.0 license",
          "license": "http://creativecommons.org/licenses/by/3.0/"
        },
        "nuts_level1": {
          "code": null,
          "name": null
        },
        "nuts_level2": {
          "code": null,
          "name": null
        },
        "nuts_level3": {
          "code": null,
          "name": null
        }
      },
      "postcode": null,
      "primary": false,
      "line": null,
      "country_geonames_id": null
    }
  ],
  "links": [
    "https://cote.labex.u-bordeaux.fr/en/Partners/UMR-BIOGECO-BIOdiversity-GEnes-COmmunities-i294.html"
  ],
  "aliases": [
    "UMR BIOGECO"
  ],
  "acronyms": [
    "BIOGECO"
  ],
  "status": "active",
  "wikipedia_url": null,
  "labels": [
    {
      "label": "BIOdiversité, GÊnes & Communautés",
      "iso639": "fr"
    }
  ],
  "country": {
    "country_name": "France",
    "country_code": "FR"
  },
  "external_ids": {
    "GRID": {
      "all": "grid.508391.6",
      "preferred": "grid.508391.6"
    },
    "ISNI": {
      "all": [
        "0000 0004 0622 9359"
      ],
      "preferred": null
    },
    "Wikidata": {
      "all": [
        "Q52606108"
      ],
      "preferred": null
    }
  }
}