{
  "id": "https://ror.org/035mqrn57",
  "name": "Centre de Sociologie des Organisations",
  "email_address": null,
  "ip_addresses": [],
  "established": 1961,
  "types": [
    "Facility"
  ],
  "relationships": [
    {
      "label": "Institut des Sciences Humaines et Sociales",
      "type": "Parent",
      "id": "https://ror.org/04b0z7q78"
    },
    {
      "label": "Institut d'Etudes Politiques de Paris",
      "type": "Parent",
      "id": "https://ror.org/05fe7ax82"
    }
  ],
  "addresses": [
    {
      "lat": 48.85341,
      "lng": 2.3488,
      "state": null,
      "state_code": null,
      "city": "Paris",
      "geonames_city": {
        "id": 2988507,
        "city": "Paris",
        "geonames_admin1": {
          "ascii_name": null,
          "code": null,
          "id": null,
          "name": null
        },
        "geonames_admin2": {
          "ascii_name": null,
          "code": null,
          "id": null,
          "name": null
        },
        "license": {
          "attribution": "Data from geonames.org under a CC-BY 3.0 license",
          "license": "http://creativecommons.org/licenses/by/3.0/"
        },
        "nuts_level1": {
          "code": null,
          "name": null
        },
        "nuts_level2": {
          "code": null,
          "name": null
        },
        "nuts_level3": {
          "code": null,
          "name": null
        }
      },
      "postcode": null,
      "primary": false,
      "line": null,
      "country_geonames_id": null
    }
  ],
  "links": [
    "https://www.sciencespo.fr/cso/"
  ],
  "aliases": [],
  "acronyms": [
    "CSO"
  ],
  "status": "active",
  "wikipedia_url": "https://en.wikipedia.org/wiki/Center_for_the_Sociology_of_Organizations",
  "labels": [
    {
      "label": "Center for the Sociology of Organizations",
      "iso639": "en"
    }
  ],
  "country": {
    "country_name": "France",
    "country_code": "FR"
  },
  "external_ids": {
    "GRID": {
      "all": "grid.473561.2",
      "preferred": "grid.473561.2"
    },
    "ISNI": {
      "all": [
        "0000 0001 1959 8282"
      ],
      "preferred": null
    },
    "Wikidata": {
      "all": [
        "Q2945496"
      ],
      "preferred": null
    }
  }
}