{
  "id": "https://ror.org/05510z802",
  "name": "Conseil régional de Bretagne",
  "email_address": null,
  "ip_addresses": [],
  "established": 1941,
  "types": [
    "Government"
  ],
  "relationships": [],
  "addresses": [
    {
      "lat": 48.11198,
      "lng": -1.67429,
      "state": null,
      "state_code": null,
      "city": "Rennes",
      "geonames_city": {
        "id": 2983990,
        "city": "Rennes",
        "geonames_admin1": {
          "ascii_name": null,
          "code": null,
          "id": null,
          "name": null
        },
        "geonames_admin2": {
          "ascii_name": null,
          "code": null,
          "id": null,
          "name": null
        },
        "license": {
          "attribution": "Data from geonames.org under a CC-BY 3.0 license",
          "license": "http://creativecommons.org/licenses/by/3.0/"
        },
        "nuts_level1": {
          "code": null,
          "name": null
        },
        "nuts_level2": {
          "code": null,
          "name": null
        },
        "nuts_level3": {
          "code": null,
          "name": null
        }
      },
      "postcode": null,
      "primary": false,
      "line": null,
      "country_geonames_id": null
    }
  ],
  "links": [
    "http://www.bretagne.bzh/jcms/JB080225_11542/fr/english"
  ],
  "aliases": [],
  "acronyms": [],
  "status": "active",
  "wikipedia_url": "https://en.wikipedia.org/wiki/Regional_Council_of_Brittany",
  "labels": [
    {
      "label": "Regional Council of Brittany",
      "iso639": "en"
    }
  ],
  "country": {
    "country_name": "France",
    "country_code": "FR"
  },
  "external_ids": {
    "FundRef": {
      "all": [
        "501100004584",
        "501100011697"
      ],
      "preferred": null
    },
    "GRID": {
      "all": "grid.468077.a",
      "preferred": "grid.468077.a"
    },
    "ISNI": {
      "all": [
        "0000 0001 2297 5966"
      ],
      "preferred": null
    }
  }
}